LICENSE
MANIFEST.in
README.md
live_plot.py
requirements.txt
setup.py
plotcat/__init__.py
plotcat/plotcat.py
plotcat.egg-info/PKG-INFO
plotcat.egg-info/SOURCES.txt
plotcat.egg-info/dependency_links.txt
plotcat.egg-info/requires.txt
plotcat.egg-info/top_level.txt