Metadata-Version: 1.0
Name: plotcat
Version: 1.0.1
Summary: tool to plot live serial input
Home-page: UNKNOWN
Author: girish joshi
Author-email: girish946@gmail.com
License: UNKNOWN
Keywords: serial input plotting realtime data matplotlib Raspberry_pi
Platform: UNKNOWN
